puf/__init__.py
puf/__main__.py
puf/ea.py
puf/json.py
puf/model.py
puf/rget.py
puf/to_html.py
puf-0.0.2.dist-info/LICENSE
puf-0.0.2.dist-info/METADATA
puf-0.0.2.dist-info/WHEEL
puf-0.0.2.dist-info/entry_points.txt
puf-0.0.2.dist-info/top_level.txt
puf-0.0.2.dist-info/RECORD
