Metadata-Version: 2.1
Name: puf
Version: 0.0.2
Summary: Python Utility Functions
Author-email: Sokrato <dlutxx@gmail.com>
Project-URL: Homepage, https://github.com/sokrato/puf
Project-URL: Bug Tracker, https://github.com/sokrato/puf/issues
Classifier: Programming Language :: Python :: 3
Classifier: License :: OSI Approved :: MIT License
Classifier: Operating System :: OS Independent
Requires-Python: >=3.7
License-File: LICENSE
Requires-Dist: requests
Provides-Extra: dev
Requires-Dist: black ; extra == 'dev'
